{
  "version": "4.5.6",
  "flags": {},
  "shapes": [
    {
      "label": "Hleucospilota",
      "points": [
        [
          139.1219512195122,
          112.1951219512195
        ],
        [
          183.6341463414634,
          65.24390243902438
        ]
      ],
      "group_id": null,
      "shape_type": "rectangle",
      "flags": {}
    },
    {
      "label": "Hatra",
      "points": [
        [
          14.121951219512194,
          374.390243902439
        ],
        [
          31,
          415
        ]
      ],
      "group_id": null,
      "shape_type": "rectangle",
      "flags": {}
    },
    {
      "label": "Hleucospilota",
      "points": [
        [
          220.21951219512192,
          157.92682926829266
        ],
        [
          264.73170731707313,
          126.21951219512194
        ]
      ],
      "group_id": null,
      "shape_type": "rectangle",
      "flags": {}
    },
    {
      "label": "Hleucospilota",
      "points": [
        [
          299.48780487804873,
          179.8780487804878
        ],
        [
          337.9024390243902,
          148.17073170731706
        ]
      ],
      "group_id": null,
      "shape_type": "rectangle",
      "flags": {}
    },
    {
      "label": "Hatra",
      "points": [
        [
          216.56097560975607,
          200.60975609756096
        ],
        [
          242.17073170731706,
          231.09756097560975
        ]
      ],
      "group_id": null,
      "shape_type": "rectangle",
      "flags": {}
    },
    {
      "label": "Hatra",
      "points": [
        [
          257.4146341463414,
          364.0243902439024
        ],
        [
          287.29268292682923,
          381.0975609756097
        ]
      ],
      "group_id": null,
      "shape_type": "rectangle",
      "flags": {}
    },
    {
      "label": "Hleucospilota",
      "points": [
        [
          293.390243902439,
          393.9024390243902
        ],
        [
          267,
          415
        ]
      ],
      "group_id": null,
      "shape_type": "rectangle",
      "flags": {}
    }
  ],
  "imagePath": "DJI_0658_0043.tif",
  "imageData": null,
  "imageHeight": 416,
  "imageWidth": 416
}