{
  "version": "4.5.6",
  "flags": {},
  "shapes": [
    {
      "label": "Hatra",
      "points": [
        [
          79.97560975609755,
          125.60975609756096
        ],
        [
          124.48780487804876,
          140.24390243902437
        ]
      ],
      "group_id": null,
      "shape_type": "rectangle",
      "flags": {}
    },
    {
      "label": "Hleucospilota",
      "points": [
        [
          122.04878048780486,
          225.60975609756096
        ],
        [
          138.5121951219512,
          293.9024390243902
        ]
      ],
      "group_id": null,
      "shape_type": "rectangle",
      "flags": {}
    },
    {
      "label": "Hatra",
      "points": [
        [
          217.78048780487802,
          153.65853658536585
        ],
        [
          204.36585365853657,
          85.97560975609755
        ]
      ],
      "group_id": null,
      "shape_type": "rectangle",
      "flags": {}
    },
    {
      "label": "Hatra",
      "points": [
        [
          243.99999999999997,
          167.0731707317073
        ],
        [
          282.4146341463414,
          150.0
        ]
      ],
      "group_id": null,
      "shape_type": "rectangle",
      "flags": {}
    },
    {
      "label": "Hleucospilota",
      "points": [
        [
          329.36585365853654,
          106.70731707317073
        ],
        [
          361.68292682926824,
          139.6341463414634
        ]
      ],
      "group_id": null,
      "shape_type": "rectangle",
      "flags": {}
    }
  ],
  "imagePath": "DJI_0097_0100.tif",
  "imageData": null,
  "imageHeight": 416,
  "imageWidth": 416
}