{
  "version": "4.5.6",
  "flags": {},
  "shapes": [
    {
      "label": "Hatra",
      "points": [
        [
          101.92682926829268,
          215.24390243902437
        ],
        [
          128.36363636363637,
          272.72727272727275
        ]
      ],
      "group_id": null,
      "shape_type": "rectangle",
      "flags": {}
    },
    {
      "label": "Hatra",
      "points": [
        [
          392.780487804878,
          199.390243902439
        ],
        [
          415.0,
          238.0
        ]
      ],
      "group_id": null,
      "shape_type": "rectangle",
      "flags": {}
    },
    {
      "label": "Hatra",
      "points": [
        [
          154.36585365853657,
          281.7073170731707
        ],
        [
          230.2775119617225,
          329.665071770335
        ]
      ],
      "group_id": null,
      "shape_type": "rectangle",
      "flags": {}
    },
    {
      "label": "Hatra",
      "points": [
        [
          120.22966507177034,
          397.12918660287085
        ],
        [
          249.89473684210526,
          338.75598086124404
        ]
      ],
      "group_id": null,
      "shape_type": "rectangle",
      "flags": {}
    }
  ],
  "imagePath": "DJI_0666_0017.tif",
  "imageData": null,
  "imageHeight": 416,
  "imageWidth": 416
}