{
  "version": "4.5.6",
  "flags": {},
  "shapes": [
    {
      "label": "Hleucospilota",
      "points": [
        [
          71.4390243902439,
          1.2195121951219512
        ],
        [
          109.85365853658536,
          76.21951219512195
        ]
      ],
      "group_id": null,
      "shape_type": "rectangle",
      "flags": {}
    },
    {
      "label": "Hatra",
      "points": [
        [
          28.14634146341463,
          331.7073170731707
        ],
        [
          75.70731707317073,
          353.6585365853658
        ]
      ],
      "group_id": null,
      "shape_type": "rectangle",
      "flags": {}
    },
    {
      "label": "Hatra",
      "points": [
        [
          307.4146341463414,
          21.341463414634145
        ],
        [
          342.780487804878,
          0.6097560975609756
        ]
      ],
      "group_id": null,
      "shape_type": "rectangle",
      "flags": {}
    },
    {
      "label": "Hatra",
      "points": [
        [
          136.0731707317073,
          405.48780487804873
        ],
        [
          219.0,
          415.0
        ]
      ],
      "group_id": null,
      "shape_type": "rectangle",
      "flags": {}
    }
  ],
  "imagePath": "DJI_0005_0080.tif",
  "imageData": null,
  "imageHeight": 416,
  "imageWidth": 416
}