{
  "version": "4.5.6",
  "flags": {},
  "shapes": [
    {
      "label": "Hatra",
      "points": [
        [
          196.12334801762114,
          296.9162995594714
        ],
        [
          286.87224669603523,
          253.7444933920705
        ]
      ],
      "group_id": null,
      "shape_type": "rectangle",
      "flags": {}
    },
    {
      "label": "Hatra",
      "points": [
        [
          31.806167400881066,
          262.55506607929516
        ],
        [
          78.06167400881057,
          292.0704845814978
        ]
      ],
      "group_id": null,
      "shape_type": "rectangle",
      "flags": {}
    },
    {
      "label": "Hatra",
      "points": [
        [
          39.73568281938327,
          384.1409691629956
        ],
        [
          0,
          411
        ]
      ],
      "group_id": null,
      "shape_type": "rectangle",
      "flags": {}
    },
    {
      "label": "Hatra",
      "points": [
        [
          251.1894273127753,
          385.9030837004405
        ],
        [
          286.87224669603523,
          360.352422907489
        ]
      ],
      "group_id": null,
      "shape_type": "rectangle",
      "flags": {}
    },
    {
      "label": "Hatra",
      "points": [
        [
          196.56387665198235,
          214.09691629955947
        ],
        [
          222.55506607929516,
          172.68722466960352
        ]
      ],
      "group_id": null,
      "shape_type": "rectangle",
      "flags": {}
    }
  ],
  "imagePath": "DJI_0996_0023.tif",
  "imageData": null,
  "imageHeight": 416,
  "imageWidth": 416
}