{
  "version": "4.5.6",
  "flags": {},
  "shapes": [
    {
      "label": "Hatra",
      "points": [
        [
          315.06607929515417,
          184.58149779735683
        ],
        [
          399.20704845814976,
          144.9339207048458
        ]
      ],
      "group_id": null,
      "shape_type": "rectangle",
      "flags": {}
    },
    {
      "label": "Hatra",
      "points": [
        [
          355.1541850220264,
          120.70484581497797
        ],
        [
          292.59911894273125,
          84.14096916299559
        ]
      ],
      "group_id": null,
      "shape_type": "rectangle",
      "flags": {}
    },
    {
      "label": "Hatra",
      "points": [
        [
          331.80616740088107,
          211.01321585903082
        ],
        [
          297.88546255506606,
          274.0088105726872
        ]
      ],
      "group_id": null,
      "shape_type": "rectangle",
      "flags": {}
    }
  ],
  "imagePath": "DJI_0915_0081.tif",
  "imageData": null,
  "imageHeight": 416,
  "imageWidth": 416
}