{
  "version": "4.5.6",
  "flags": {},
  "shapes": [
    {
      "label": "Hatra",
      "points": [
        [
          81.58590308370043,
          285.0220264317181
        ],
        [
          33.56828193832598,
          340.96916299559473
        ]
      ],
      "group_id": null,
      "shape_type": "rectangle",
      "flags": {}
    },
    {
      "label": "Hatra",
      "points": [
        [
          252.0704845814978,
          244.9339207048458
        ],
        [
          286.431718061674,
          325.1101321585903
        ]
      ],
      "group_id": null,
      "shape_type": "rectangle",
      "flags": {}
    }
  ],
  "imagePath": "DJI_0927_0022.tif",
  "imageData": null,
  "imageHeight": 416,
  "imageWidth": 416
}