{
  "version": "4.5.6",
  "flags": {},
  "shapes": [
    {
      "label": "Hleucospilota",
      "points": [
        [
          180.2905982905983,
          346.5811965811966
        ],
        [
          155.93162393162393,
          272.22222222222223
        ]
      ],
      "group_id": null,
      "shape_type": "rectangle",
      "flags": {}
    },
    {
      "label": "Hleucospilota",
      "points": [
        [
          115.33333333333334,
          243.5897435897436
        ],
        [
          161.05982905982907,
          303.84615384615387
        ]
      ],
      "group_id": null,
      "shape_type": "rectangle",
      "flags": {}
    },
    {
      "label": "Hatra",
      "points": [
        [
          253.36752136752136,
          329.0598290598291
        ],
        [
          296.95726495726495,
          352.13675213675214
        ]
      ],
      "group_id": null,
      "shape_type": "rectangle",
      "flags": {}
    }
  ],
  "imagePath": "DJI_0359_0020.tif",
  "imageData": null,
  "imageHeight": 416,
  "imageWidth": 416
}