{
  "version": "4.5.6",
  "flags": {},
  "shapes": [
    {
      "label": "Hatra",
      "points": [
        [
          197.65853658536585,
          112.1951219512195
        ],
        [
          173.2682926829268,
          156.7073170731707
        ]
      ],
      "group_id": null,
      "shape_type": "rectangle",
      "flags": {}
    },
    {
      "label": "Hatra",
      "points": [
        [
          18.999999999999996,
          129.8780487804878
        ],
        [
          0.0,
          179.0
        ]
      ],
      "group_id": null,
      "shape_type": "rectangle",
      "flags": {}
    },
    {
      "label": "Hatra",
      "points": [
        [
          146.4390243902439,
          176.8292682926829
        ],
        [
          200.09756097560975,
          228.04878048780486
        ]
      ],
      "group_id": null,
      "shape_type": "rectangle",
      "flags": {}
    },
    {
      "label": "Hatra",
      "points": [
        [
          295.8292682926829,
          239.02439024390242
        ],
        [
          234.24390243902437,
          265.8536585365853
        ]
      ],
      "group_id": null,
      "shape_type": "rectangle",
      "flags": {}
    },
    {
      "label": "Hleucospilota",
      "points": [
        [
          225.09756097560975,
          56.09756097560975
        ],
        [
          260.4634146341463,
          96.95121951219511
        ]
      ],
      "group_id": null,
      "shape_type": "rectangle",
      "flags": {}
    },
    {
      "label": "Hatra",
      "points": [
        [
          379.36585365853654,
          160.97560975609755
        ],
        [
          321.4390243902439,
          94.51219512195121
        ]
      ],
      "group_id": null,
      "shape_type": "rectangle",
      "flags": {}
    },
    {
      "label": "Hatra",
      "points": [
        [
          68.39024390243902,
          356.0975609756097
        ],
        [
          59.24390243902438,
          311.5853658536585
        ]
      ],
      "group_id": null,
      "shape_type": "rectangle",
      "flags": {}
    }
  ],
  "imagePath": "DJI_0081_0014.tif",
  "imageData": null,
  "imageHeight": 416,
  "imageWidth": 416
}