{
  "version": "4.5.6",
  "flags": {},
  "shapes": [
    {
      "label": "Hatra",
      "points": [
        [
          179.97560975609755,
          212.80487804878047
        ],
        [
          209.24390243902437,
          163.41463414634146
        ]
      ],
      "group_id": null,
      "shape_type": "rectangle",
      "flags": {}
    },
    {
      "label": "Hleucospilota",
      "points": [
        [
          272.04878048780483,
          225.60975609756096
        ],
        [
          293.390243902439,
          240.85365853658536
        ]
      ],
      "group_id": null,
      "shape_type": "rectangle",
      "flags": {}
    },
    {
      "label": "Other",
      "points": [
        [
          53.756097560975604,
          219.5121951219512
        ],
        [
          73.26829268292683,
          192.68292682926827
        ]
      ],
      "group_id": null,
      "shape_type": "rectangle",
      "flags": {}
    }
  ],
  "imagePath": "DJI_0158_0008.tif",
  "imageData": null,
  "imageHeight": 416,
  "imageWidth": 416
}