{
  "version": "4.5.6",
  "flags": {},
  "shapes": [
    {
      "label": "Hatra",
      "points": [
        [
          1.3170731707317067,
          328.6585365853658
        ],
        [
          28.756097560975604,
          282.92682926829264
        ]
      ],
      "group_id": null,
      "shape_type": "rectangle",
      "flags": {}
    },
    {
      "label": "Hleucospilota",
      "points": [
        [
          0.7073170731707314,
          393.9024390243902
        ],
        [
          32.0,
          415.0
        ]
      ],
      "group_id": null,
      "shape_type": "rectangle",
      "flags": {}
    },
    {
      "label": "Hatra",
      "points": [
        [
          60.46341463414633,
          139.02439024390242
        ],
        [
          108.6341463414634,
          96.95121951219511
        ]
      ],
      "group_id": null,
      "shape_type": "rectangle",
      "flags": {}
    },
    {
      "label": "Hatra",
      "points": [
        [
          225.7073170731707,
          153.04878048780486
        ],
        [
          242.17073170731706,
          110.36585365853658
        ]
      ],
      "group_id": null,
      "shape_type": "rectangle",
      "flags": {}
    },
    {
      "label": "Hleucospilota",
      "points": [
        [
          401.92682926829264,
          124.39024390243901
        ],
        [
          415.0,
          101.0
        ]
      ],
      "group_id": null,
      "shape_type": "rectangle",
      "flags": {}
    },
    {
      "label": "Hatra",
      "points": [
        [
          384.24390243902434,
          250.60975609756096
        ],
        [
          415,
          288
        ]
      ],
      "group_id": null,
      "shape_type": "rectangle",
      "flags": {}
    }
  ],
  "imagePath": "DJI_0575_0027.tif",
  "imageData": null,
  "imageHeight": 416,
  "imageWidth": 416
}