{
  "version": "4.5.6",
  "flags": {},
  "shapes": [
    {
      "label": "Hleucospilota",
      "points": [
        [
          8.634146341463413,
          229.2682926829268
        ],
        [
          53.756097560975604,
          165.24390243902437
        ]
      ],
      "group_id": null,
      "shape_type": "rectangle",
      "flags": {}
    },
    {
      "label": "Hatra",
      "points": [
        [
          133.02439024390242,
          67.68292682926828
        ],
        [
          104.97560975609755,
          96.95121951219511
        ]
      ],
      "group_id": null,
      "shape_type": "rectangle",
      "flags": {}
    },
    {
      "label": "Hatra",
      "points": [
        [
          337.9024390243902,
          383.5365853658536
        ],
        [
          370,
          415
        ]
      ],
      "group_id": null,
      "shape_type": "rectangle",
      "flags": {}
    },
    {
      "label": "Hleucospilota",
      "points": [
        [
          401.92682926829264,
          280.48780487804873
        ],
        [
          415,
          266
        ]
      ],
      "group_id": null,
      "shape_type": "rectangle",
      "flags": {}
    }
  ],
  "imagePath": "DJI_0575_0074.tif",
  "imageData": null,
  "imageHeight": 416,
  "imageWidth": 416
}