{
  "version": "4.5.6",
  "flags": {},
  "shapes": [
    {
      "label": "Hatra",
      "points": [
        [
          355.5853658536585,
          137.1951219512195
        ],
        [
          293.390243902439,
          186.58536585365852
        ]
      ],
      "group_id": null,
      "shape_type": "rectangle",
      "flags": {}
    },
    {
      "label": "Hatra",
      "points": [
        [
          272.04878048780483,
          268.29268292682923
        ],
        [
          319.60975609756093,
          235.36585365853657
        ]
      ],
      "group_id": null,
      "shape_type": "rectangle",
      "flags": {}
    }
  ],
  "imagePath": "DJI_0009_0018.tif",
  "imageData": null,
  "imageHeight": 416,
  "imageWidth": 416
}