{
  "version": "4.5.6",
  "flags": {},
  "shapes": [
    {
      "label": "Hleucospilota",
      "points": [
        [
          403.1463414634146,
          371.9512195121951
        ],
        [
          356.1951219512195,
          325.0
        ]
      ],
      "group_id": null,
      "shape_type": "rectangle",
      "flags": {}
    },
    {
      "label": "Hleucospilota",
      "points": [
        [
          393.99999999999994,
          295.1219512195122
        ],
        [
          415,
          330
        ]
      ],
      "group_id": null,
      "shape_type": "rectangle",
      "flags": {}
    }
  ],
  "imagePath": "DJI_0666_0060.tif",
  "imageData": null,
  "imageHeight": 416,
  "imageWidth": 416
}