{
  "version": "4.5.6",
  "flags": {},
  "shapes": [
    {
      "label": "Hleucospilota",
      "points": [
        [
          226.92682926829266,
          42.073170731707314
        ],
        [
          291.5609756097561,
          123.78048780487804
        ]
      ],
      "group_id": null,
      "shape_type": "rectangle",
      "flags": {}
    },
    {
      "label": "Hatra",
      "points": [
        [
          209.85365853658536,
          351.8292682926829
        ],
        [
          252.53658536585363,
          334.1463414634146
        ]
      ],
      "group_id": null,
      "shape_type": "rectangle",
      "flags": {}
    },
    {
      "label": "Hatra",
      "points": [
        [
          364.12195121951214,
          328.04878048780483
        ],
        [
          404.36585365853654,
          344.5121951219512
        ]
      ],
      "group_id": null,
      "shape_type": "rectangle",
      "flags": {}
    }
  ],
  "imagePath": "DJI_0081_0038.tif",
  "imageData": null,
  "imageHeight": 416,
  "imageWidth": 416
}