{
  "version": "4.5.6",
  "flags": {},
  "shapes": [
    {
      "label": "Hatra",
      "points": [
        [
          72.26431718061674,
          18.502202643171806
        ],
        [
          40.546255506607935,
          91.18942731277534
        ]
      ],
      "group_id": null,
      "shape_type": "rectangle",
      "flags": {}
    },
    {
      "label": "Hatra",
      "points": [
        [
          17.19823788546256,
          278.8546255506608
        ],
        [
          66.53744493392071,
          316.7400881057269
        ]
      ],
      "group_id": null,
      "shape_type": "rectangle",
      "flags": {}
    },
    {
      "label": "Hatra",
      "points": [
        [
          168.29955947136563,
          300.0
        ],
        [
          201.33920704845815,
          347.13656387665196
        ]
      ],
      "group_id": null,
      "shape_type": "rectangle",
      "flags": {}
    },
    {
      "label": "Hleucospilota",
      "points": [
        [
          392.52863436123346,
          164.31718061674007
        ],
        [
          352.8810572687225,
          225.11013215859032
        ]
      ],
      "group_id": null,
      "shape_type": "rectangle",
      "flags": {}
    }
  ],
  "imagePath": "DJI_0178_0044.tif",
  "imageData": null,
  "imageHeight": 416,
  "imageWidth": 416
}