{
  "version": "4.5.6",
  "flags": {},
  "shapes": [
    {
      "label": "Hatra",
      "points": [
        [
          1.926829268292682,
          52.4390243902439
        ],
        [
          32.41463414634146,
          71.34146341463413
        ]
      ],
      "group_id": null,
      "shape_type": "rectangle",
      "flags": {}
    },
    {
      "label": "Hatra",
      "points": [
        [
          248.2682926829268,
          70.73170731707316
        ],
        [
          265.3414634146341,
          99.39024390243901
        ]
      ],
      "group_id": null,
      "shape_type": "rectangle",
      "flags": {}
    },
    {
      "label": "Hatra",
      "points": [
        [
          44.609756097560975,
          185.97560975609755
        ],
        [
          73.8780487804878,
          212.1951219512195
        ]
      ],
      "group_id": null,
      "shape_type": "rectangle",
      "flags": {}
    },
    {
      "label": "Hatra",
      "points": [
        [
          231.80487804878047,
          175.0
        ],
        [
          252.53658536585363,
          201.21951219512192
        ]
      ],
      "group_id": null,
      "shape_type": "rectangle",
      "flags": {}
    },
    {
      "label": "Hleucospilota",
      "points": [
        [
          222.04878048780486,
          210.97560975609755
        ],
        [
          255.58536585365852,
          231.7073170731707
        ]
      ],
      "group_id": null,
      "shape_type": "rectangle",
      "flags": {}
    },
    {
      "label": "Hleucospilota",
      "points": [
        [
          211.68292682926827,
          235.36585365853657
        ],
        [
          241.56097560975607,
          277.4390243902439
        ]
      ],
      "group_id": null,
      "shape_type": "rectangle",
      "flags": {}
    },
    {
      "label": "Hatra",
      "points": [
        [
          272.6585365853658,
          173.17073170731706
        ],
        [
          250.09756097560972,
          194.5121951219512
        ]
      ],
      "group_id": null,
      "shape_type": "rectangle",
      "flags": {}
    },
    {
      "label": "Hatra",
      "points": [
        [
          303.7560975609756,
          63.414634146341456
        ],
        [
          323.2682926829268,
          78.04878048780488
        ]
      ],
      "group_id": null,
      "shape_type": "rectangle",
      "flags": {}
    },
    {
      "label": "Hleucospilota",
      "points": [
        [
          393.390243902439,
          111.58536585365853
        ],
        [
          415.0,
          141.0
        ]
      ],
      "group_id": null,
      "shape_type": "rectangle",
      "flags": {}
    },
    {
      "label": "Hleucospilota",
      "points": [
        [
          237.29268292682926,
          340.8536585365853
        ],
        [
          278.1463414634146,
          325.0
        ]
      ],
      "group_id": null,
      "shape_type": "rectangle",
      "flags": {}
    }
  ],
  "imagePath": "DJI_0595_0058.tif",
  "imageData": null,
  "imageHeight": 416,
  "imageWidth": 416
}