{
  "version": "4.5.6",
  "flags": {},
  "shapes": [
    {
      "label": "other",
      "points": [
        [
          7.136563876651991,
          319.8237885462555
        ],
        [
          63.083700440528645,
          351.10132158590307
        ]
      ],
      "group_id": null,
      "shape_type": "rectangle",
      "flags": {}
    },
    {
      "label": "Hatra",
      "points": [
        [
          43.700440528634374,
          211.01321585903082
        ],
        [
          1.850220264317187,
          244.05286343612335
        ]
      ],
      "group_id": null,
      "shape_type": "rectangle",
      "flags": {}
    },
    {
      "label": "Hatra",
      "points": [
        [
          287.31277533039645,
          41.409691629955944
        ],
        [
          256.9162995594714,
          110.57268722466961
        ]
      ],
      "group_id": null,
      "shape_type": "rectangle",
      "flags": {}
    },
    {
      "label": "Hatra",
      "points": [
        [
          382.02643171806164,
          55.06607929515418
        ],
        [
          415,
          38
        ]
      ],
      "group_id": null,
      "shape_type": "rectangle",
      "flags": {}
    }
  ],
  "imagePath": "DJI_0674_0020.tif",
  "imageData": null,
  "imageHeight": 416,
  "imageWidth": 416
}