{
  "version": "4.5.6",
  "flags": {},
  "shapes": [
    {
      "label": "Hatra",
      "points": [
        [
          51.18942731277534,
          49.779735682819386
        ],
        [
          31.806167400881066,
          0.8810572687224669
        ]
      ],
      "group_id": null,
      "shape_type": "rectangle",
      "flags": {}
    },
    {
      "label": "Hatra",
      "points": [
        [
          263.5242290748899,
          277.09251101321587
        ],
        [
          219.03083700440527,
          319.38325991189424
        ]
      ],
      "group_id": null,
      "shape_type": "rectangle",
      "flags": {}
    },
    {
      "label": "Hatra",
      "points": [
        [
          402.29074889867843,
          150.2202643171806
        ],
        [
          415,
          131
        ]
      ],
      "group_id": null,
      "shape_type": "rectangle",
      "flags": {}
    }
  ],
  "imagePath": "DJI_0992_0106.tif",
  "imageData": null,
  "imageHeight": 416,
  "imageWidth": 416
}