{
  "version": "4.5.6",
  "flags": {},
  "shapes": [
    {
      "label": "Hleucospilota",
      "points": [
        [
          198.2682926829268,
          55.48780487804878
        ],
        [
          256.8048780487805,
          81.09756097560975
        ]
      ],
      "group_id": null,
      "shape_type": "rectangle",
      "flags": {}
    },
    {
      "label": "Hatra",
      "points": [
        [
          392.17073170731703,
          374.99999999999994
        ],
        [
          415.0,
          356.0
        ]
      ],
      "group_id": null,
      "shape_type": "rectangle",
      "flags": {}
    }
  ],
  "imagePath": "DJI_0017_0022.tif",
  "imageData": null,
  "imageHeight": 416,
  "imageWidth": 416
}