{
  "version": "4.5.6",
  "flags": {},
  "shapes": [
    {
      "label": "Hatra",
      "points": [
        [
          50.09756097560975,
          92.68292682926828
        ],
        [
          91.56097560975608,
          123.17073170731706
        ]
      ],
      "group_id": null,
      "shape_type": "rectangle",
      "flags": {}
    },
    {
      "label": "Hatra",
      "points": [
        [
          181.1951219512195,
          217.68292682926827
        ],
        [
          233.6341463414634,
          245.73170731707316
        ]
      ],
      "group_id": null,
      "shape_type": "rectangle",
      "flags": {}
    },
    {
      "label": "Hleucospilota",
      "points": [
        [
          333.0243902439024,
          153.65853658536585
        ],
        [
          379.9756097560975,
          208.53658536585365
        ]
      ],
      "group_id": null,
      "shape_type": "rectangle",
      "flags": {}
    },
    {
      "label": "Hleucospilota",
      "points": [
        [
          347.6585365853658,
          264.6341463414634
        ],
        [
          368.99999999999994,
          323.780487804878
        ]
      ],
      "group_id": null,
      "shape_type": "rectangle",
      "flags": {}
    },
    {
      "label": "Hleucospilota",
      "points": [
        [
          396.43902439024384,
          113.41463414634146
        ],
        [
          415,
          73
        ]
      ],
      "group_id": null,
      "shape_type": "rectangle",
      "flags": {}
    }
  ],
  "imagePath": "DJI_0085_0033.tif",
  "imageData": null,
  "imageHeight": 416,
  "imageWidth": 416
}