{
  "version": "4.5.6",
  "flags": {},
  "shapes": [
    {
      "label": "Hleucospilota",
      "points": [
        [
          211.68292682926827,
          96.95121951219511
        ],
        [
          248.87804878048777,
          112.1951219512195
        ]
      ],
      "group_id": null,
      "shape_type": "rectangle",
      "flags": {}
    },
    {
      "label": "Hatra",
      "points": [
        [
          378.1463414634146,
          37.80487804878049
        ],
        [
          348.2682926829268,
          2.4390243902439024
        ]
      ],
      "group_id": null,
      "shape_type": "rectangle",
      "flags": {}
    },
    {
      "label": "Hatra",
      "points": [
        [
          322.04878048780483,
          229.87804878048777
        ],
        [
          294.60975609756093,
          278.04878048780483
        ]
      ],
      "group_id": null,
      "shape_type": "rectangle",
      "flags": {}
    },
    {
      "label": "Hatra",
      "points": [
        [
          395.2195121951219,
          169.5121951219512
        ],
        [
          413.5121951219512,
          208.53658536585365
        ]
      ],
      "group_id": null,
      "shape_type": "rectangle",
      "flags": {}
    }
  ],
  "imagePath": "DJI_0579_0026.tif",
  "imageData": null,
  "imageHeight": 416,
  "imageWidth": 416
}