{
  "version": "4.5.6",
  "flags": {},
  "shapes": [
    {
      "label": "Hatra",
      "points": [
        [
          128.72246696035245,
          9.691629955947137
        ],
        [
          63.083700440528645,
          69.16299559471365
        ]
      ],
      "group_id": null,
      "shape_type": "rectangle",
      "flags": {}
    },
    {
      "label": "Hatra",
      "points": [
        [
          53.83259911894274,
          109.2511013215859
        ],
        [
          129.16299559471366,
          68.28193832599119
        ]
      ],
      "group_id": null,
      "shape_type": "rectangle",
      "flags": {}
    },
    {
      "label": "Hatra",
      "points": [
        [
          201.40969162995594,
          61.67400881057269
        ],
        [
          173.215859030837,
          100.44052863436123
        ]
      ],
      "group_id": null,
      "shape_type": "rectangle",
      "flags": {}
    },
    {
      "label": "Hatra",
      "points": [
        [
          358.2378854625551,
          198.6784140969163
        ],
        [
          292.15859030837004,
          248.01762114537445
        ]
      ],
      "group_id": null,
      "shape_type": "rectangle",
      "flags": {}
    },
    {
      "label": "Hleucospilota",
      "points": [
        [
          283.7885462555066,
          372.6872246696035
        ],
        [
          334.44933920704847,
          333.92070484581495
        ]
      ],
      "group_id": null,
      "shape_type": "rectangle",
      "flags": {}
    },
    {
      "label": "Hatra",
      "points": [
        [
          143.70044052863437,
          384.1409691629956
        ],
        [
          94.3612334801762,
          343.61233480176213
        ]
      ],
      "group_id": null,
      "shape_type": "rectangle",
      "flags": {}
    }
  ],
  "imagePath": "DJI_0670_0043.tif",
  "imageData": null,
  "imageHeight": 416,
  "imageWidth": 416
}