{
  "version": "4.5.6",
  "flags": {},
  "shapes": [
    {
      "label": "Hatra",
      "points": [
        [
          234.44933920704847,
          388.1057268722467
        ],
        [
          201.40969162995594,
          414.9779735682819
        ]
      ],
      "group_id": null,
      "shape_type": "rectangle",
      "flags": {}
    },
    {
      "label": "Hatra",
      "points": [
        [
          19.471365638766514,
          391.6299559471366
        ],
        [
          43.700440528634374,
          414.9779735682819
        ]
      ],
      "group_id": null,
      "shape_type": "rectangle",
      "flags": {}
    }
  ],
  "imagePath": "DJI_0923_0007.tif",
  "imageData": null,
  "imageHeight": 416,
  "imageWidth": 416
}