{
  "version": "4.5.6",
  "flags": {},
  "shapes": [
    {
      "label": "Hatra",
      "points": [
        [
          1.3170731707317067,
          41.46341463414634
        ],
        [
          23.878048780487802,
          102.4390243902439
        ]
      ],
      "group_id": null,
      "shape_type": "rectangle",
      "flags": {}
    },
    {
      "label": "Hatra",
      "points": [
        [
          192.17073170731706,
          0.6097560975609756
        ],
        [
          221.43902439024387,
          15.853658536585364
        ]
      ],
      "group_id": null,
      "shape_type": "rectangle",
      "flags": {}
    },
    {
      "label": "Hatra",
      "points": [
        [
          121.43902439024389,
          76.21951219512195
        ],
        [
          86.07317073170731,
          100.60975609756096
        ]
      ],
      "group_id": null,
      "shape_type": "rectangle",
      "flags": {}
    },
    {
      "label": "Hatra",
      "points": [
        [
          106.1951219512195,
          91.46341463414633
        ],
        [
          123.26829268292681,
          157.92682926829266
        ]
      ],
      "group_id": null,
      "shape_type": "rectangle",
      "flags": {}
    },
    {
      "label": "Hleucospilota",
      "points": [
        [
          133.02439024390242,
          127.43902439024389
        ],
        [
          153.14634146341461,
          189.02439024390242
        ]
      ],
      "group_id": null,
      "shape_type": "rectangle",
      "flags": {}
    },
    {
      "label": "Hatra",
      "points": [
        [
          11.68292682926829,
          242.0731707317073
        ],
        [
          53.14634146341463,
          279.8780487804878
        ]
      ],
      "group_id": null,
      "shape_type": "rectangle",
      "flags": {}
    },
    {
      "label": "Hatra",
      "points": [
        [
          24.487804878048777,
          284.1463414634146
        ],
        [
          0.0,
          320.0
        ]
      ],
      "group_id": null,
      "shape_type": "rectangle",
      "flags": {}
    },
    {
      "label": "Hatra",
      "points": [
        [
          178.14634146341461,
          170.73170731707316
        ],
        [
          153.14634146341461,
          189.02439024390242
        ]
      ],
      "group_id": null,
      "shape_type": "rectangle",
      "flags": {}
    },
    {
      "label": "Hatra",
      "points": [
        [
          210.46341463414632,
          387.80487804878044
        ],
        [
          191.56097560975607,
          414.6341463414634
        ]
      ],
      "group_id": null,
      "shape_type": "rectangle",
      "flags": {}
    }
  ],
  "imagePath": "DJI_0073_0095.tif",
  "imageData": null,
  "imageHeight": 416,
  "imageWidth": 416
}